stringbrewer/__init__.py
stringbrewer-0.0.1.dist-info/METADATA
stringbrewer-0.0.1.dist-info/WHEEL
stringbrewer-0.0.1.dist-info/top_level.txt
stringbrewer-0.0.1.dist-info/RECORD
