Metadata-Version: 2.1
Name: stringbrewer
Version: 0.0.1
Summary: Generate random strings matching a pattern
Home-page: https://github.com/simoncozens/stringbrewer
Author: Simon Cozens
Author-email: simon@simon-cozens.org
License: MIT
Platform: UNKNOWN
Classifier: Programming Language :: Python
Classifier: Programming Language :: Python :: 2
Classifier: Programming Language :: Python :: 3
Classifier: License :: OSI Approved :: MIT License
Classifier: Development Status :: 4 - Beta
